meety/__init__.py
meety/__main__.py
meety/args.py
meety/config.py
meety/loader.py
meety/logging.py
meety/resources.py
meety/cli/__init__.py
meety/cli/app.py
meety/cli/args.py
meety/cli/styles.py
meety/cli/utils.py
meety/connect/__init__.py
meety/connect/handlers.py
meety/gui/__init__.py
meety/gui/app.py
meety/gui/args.py
meety/gui/icons.py
meety/gui/styles.py
meety/gui/info_dialog/__init__.py
meety/gui/info_dialog/about.py
meety/gui/info_dialog/files.py
meety/gui/info_dialog/log.py
meety/gui/info_dialog/meetings.py
meety/gui/info_dialog/system.py
meety/gui/main_window/__init__.py
meety/gui/main_window/main_window.py
meety/gui/main_window/options.py
meety/gui/main_window/search.py
meety/gui/main_window/status.py
meety/gui/main_window/meeting_list/__init__.py
meety/gui/main_window/meeting_list/context.py
meety/gui/main_window/meeting_list/delegate.py
meety/gui/main_window/meeting_list/item.py
meety/gui/main_window/meeting_list/list.py
meety/gui/meeting_dialog/__init__.py
meety/gui/meeting_dialog/addmode.py
meety/gui/meeting_dialog/yamlimport.py
meety/gui/static/__init__.py
meety/gui/static/stylesheet.css
meety/io/__init__.py
meety/io/html.py
meety/io/utils.py
meety/io/actions/__init__.py
meety/io/actions/action.py
meety/io/actions/infer.py
meety/io/actions/registry.py
meety/io/actions/replace.py
meety/io/actions/strip.py
meety/io/actions/synonym.py
meety/io/datetime/__init__.py
meety/io/datetime/weekday_translations.py
meety/meetings/__init__.py
meety/meetings/meeting.py
meety/meetings/preferences.py
meety/meetings/rating.py
meety/meetings/utils.py
meety/static/__init__.py
meety/static/config/__init__.py
meety/static/config/col_blue.yaml
meety/static/config/col_green.yaml
meety/static/config/col_magenta.yaml
meety/static/config/defaults.yaml
meety/static/config/lang_de.yaml
meety/static/config/lang_en.yaml
meety/static/config/lang_es.yaml
meety/static/config/lang_fr.yaml
meety/static/config/lang_it.yaml
meety/static/config/time_dmy.yaml
meety-0.11.0.dist-info/LICENSE
meety-0.11.0.dist-info/METADATA
meety-0.11.0.dist-info/WHEEL
meety-0.11.0.dist-info/entry_points.txt
meety-0.11.0.dist-info/top_level.txt
meety-0.11.0.dist-info/RECORD
