Metadata-Version: 2.1
Name: meety
Version: 0.11.0
Summary: Quickly start online meetings from YAML
Home-page: https://github.com/GaetanoGeck/meety
Author: Gaetano Geck
Author-email: gaetano.geck@cs.tu-dortmund.de
License: GPLv3+
Platform: UNKNOWN
Classifier: Development Status :: 5 - Production/Stable
Classifier: License :: OSI Approved :: GNU General Public License v3 or later (GPLv3+)
Classifier: Operating System :: MacOS
Classifier: Operating System :: Microsoft :: Windows
Classifier: Operating System :: POSIX :: Linux
Classifier: Topic :: Communications
Requires-Dist: appdirs
Requires-Dist: pyyaml
Requires-Dist: pyperclip
Requires-Dist: termcolor
Requires-Dist: colorama
Requires-Dist: pyqt5
Requires-Dist: pyshortcuts (>="1.8.0")
